kellanb_cryptography/__init__.py
kellanb_cryptography/aes.py
kellanb_cryptography/chacha20.py
kellanb_cryptography/easy.py
kellanb_cryptography/hash.py
kellanb_cryptography/hmac.py
kellanb_cryptography/key.py
kellanb_cryptography-1.2.3.dist-info/METADATA
kellanb_cryptography-1.2.3.dist-info/WHEEL
kellanb_cryptography-1.2.3.dist-info/top_level.txt
kellanb_cryptography-1.2.3.dist-info/RECORD
