Metadata-Version: 2.1
Name: kellanb_cryptography
Version: 1.2.3
Summary: encryption libray
Home-page: UNKNOWN
Author: Kellan Butler
Author-email: kellanbulter52@gmial.com
License: UNKNOWN
Project-URL: Source, https://github.com/kellantech/kellanb-cryptography
Keywords: python,encryption,aes,chacha20,hmac
Platform: UNKNOWN
Classifier: Development Status :: 5 - Production/Stable
Classifier: Intended Audience :: Developers
Classifier: Programming Language :: Python :: 3
Classifier: Operating System :: POSIX :: Linux
Classifier: Operating System :: Microsoft :: Windows
Classifier: Operating System :: MacOS
